{
  "authors": [
    {
      "id": "999e3044-6a1e-4c20-909a-aa41d09bc001",
      "name": "Noah Putnam",
      "headshotUri": "https://s3.amazonaws.com/megaphone-logo-uploads/defaultUser.png",
      "bio": "Bio for Noah Putnam."
    }
  ],
  "posts": [],
  "tags": {
    "5558f9eb-1617-4f18-a1f8-d48175e79ae0": {
      "name": "real Tag",
      "description": "Description of real tag."
    }
  },
  "data": {
    "title": "Title of real Blog",
    "name": "Name of real Blog",
    "description": "Description of real blog.",
    "headerPhotoUri": "https://s3.amazonaws.com/megaphone-logo-uploads/defaultLogo.png",
    "sidebarPhotoUri": "https://s3.amazonaws.com/megaphone-logo-uploads/defaultLogo.png",
    "bgImgUri": "https://s3.amazonaws.com/megaphone-logo-uploads/defaultLogo.png",
    "backgroundHexCode": "#ffffff",
    "mainSiteUrl": "https://www.blogwise.co/",
    "twitterUrl": "https://twitter.com/",
    "facebookUrl": "https://www.facebook.com/",
    "linkedinUrl": "https://www.linkedin.com/"
  }
}
